jupyter_marimo_server/__init__.py
jupyter_marimo_server/icons/marimo.svg
jupyter_marimo_server-0.1.3.dist-info/METADATA
jupyter_marimo_server-0.1.3.dist-info/WHEEL
jupyter_marimo_server-0.1.3.dist-info/entry_points.txt
jupyter_marimo_server-0.1.3.dist-info/top_level.txt
jupyter_marimo_server-0.1.3.dist-info/RECORD
