Metadata-Version: 2.4
Name: jupyter-marimo-server
Version: 0.1.3
Summary: Launch Marimo notebooks from Jupyter
Requires-Python: >=3.10
Requires-Dist: jupyter-server-proxy>=1.4.0
Requires-Dist: jupyterlab>=4.5.1
Requires-Dist: marimo>=0.18.4
